{
  "name": "Generated Schematic",
  "box_dims": [
    200.0,
    100.0
  ],
  "box_outline": [
    [
      [
        0.0,
        0.0
      ],
      [
        200.0,
        0.0
      ]
    ],
    [
      [
        200.0,
        0.0
      ],
      [
        200.0,
        100.0
      ]
    ],
    [
      [
        200.0,
        100.0
      ],
      [
        0.0,
        100.0
      ]
    ],
    [
      [
        0.0,
        100.0
      ],
      [
        0.0,
        0.0
      ]
    ]
  ],
  "nodes": [
    {
      "id": "node_0",
      "kind": "Inlet",
      "point": [
        0.0,
        50.0
      ]
    },
    {
      "id": "node_1",
      "kind": "Outlet",
      "point": [
        200.0,
        50.0
      ]
    }
  ],
  "channels": [
    {
      "id": "ch_0",
      "kind": "Pipe",
      "from": "node_0",
      "to": "node_1",
      "length_m": 0.23359641747914034,
      "cross_section": {
        "Rectangular": {
          "width_m": 0.001,
          "height_m": 0.0005
        }
      },
      "channel_shape": {
        "Serpentine": {
          "segments": 5,
          "bend_radius_m": 0.0013908208706653314
        }
      },
      "resistance": 0.0,
      "quad_coeff": 0.0,
      "valve_cv": null,
      "pump_max_flow": null,
      "pump_max_pressure": null,
      "visual_role": null,
      "path": [
        [
          0.0,
          50.0
        ],
        [
          1.0050251256281406,
          50.000000000734545
        ],
        [
          2.0100502512562812,
          50.000000314720786
        ],
        [
          3.015075376884422,
          50.00001002389728
        ],
        [
          4.0201005025125625,
          50.000109358809624
        ],
        [
          5.025125628140704,
          50.00065882558978
        ],
        [
          6.030150753768844,
          50.00270745778417
        ],
        [
          7.035175879396985,
          50.00848116276405
        ],
        [
          8.040201005025125,
          50.02159221084661
        ],
        [
          9.045226130653267,
          50.046422836524336
        ],
        [
          10.050251256281408,
          50.00000000000088
        ],
        [
          11.055276381909549,
          50.000000280641835
        ],
        [
          12.060301507537687,
          50.00000625143134
        ],
        [
          13.06532663316583,
          50.000044294553575
        ],
        [
          14.07035175879397,
          50.000189003092885
        ],
        [
          15.07537688442211,
          50.00059783497348
        ],
        [
          16.08040201005025,
          50.00154114572498
        ],
        [
          17.08542713567839,
          50.00340795924489
        ],
        [
          18.090452261306535,
          50.00666436331196
        ],
        [
          19.09547738693467,
          50.01174588228426
        ],
        [
          20.100502512562816,
          50.01888054576553
        ],
        [
          21.105527638190953,
          50.02809063233169
        ],
        [
          22.110552763819097,
          50.04016448242469
        ],
        [
          23.115577889447238,
          50.05567680148026
        ],
        [
          24.120603015075375,
          50.07514345794371
        ],
        [
          25.125628140703515,
          50.099071526493006
        ],
        [
          26.13065326633166,
          50.127944528663626
        ],
        [
          27.1356783919598,
          50.162206958297375
        ],
        [
          28.14070351758794,
          50.20224835266457
        ],
        [
          29.145728643216078,
          50.24838717821301
        ],
        [
          30.15075376884422,
          50.30085480512782
        ],
        [
          31.155778894472363,
          50.359779847189834
        ],
        [
          32.1608040201005,
          50.425173142767065
        ],
        [
          33.165829145728644,
          50.496913649160305
        ],
        [
          34.17085427135678,
          50.574735515972016
        ],
        [
          35.175879396984925,
          50.65821659372499
        ],
        [
          36.18090452261307,
          50.746768621695054
        ],
        [
          37.185929648241206,
          50.8396293239391
        ],
        [
          38.19095477386934,
          50.93585662491479
        ],
        [
          39.19597989949749,
          51.03432517604662
        ],
        [
          40.20100502512563,
          51.133725362259554
        ],
        [
          41.20603015075377,
          51.23256493306258
        ],
        [
          42.211055276381906,
          51.32917337642582
        ],
        [
          43.21608040201005,
          51.421709125679655
        ],
        [
          44.221105527638194,
          50.00825734531151
        ],
        [
          45.22613065326633,
          50.08145672316461
        ],
        [
          46.231155778894475,
          50.23088070428614
        ],
        [
          47.23618090452261,
          50.456577195259804
        ],
        [
          48.24120603015075,
          50.75789725795918
        ],
        [
          49.246231155778894,
          51.133499236497855
        ],
        [
          50.25125628140703,
          51.58135833988985
        ],
        [
          51.256281407035175,
          52.09878160734005
        ],
        [
          52.26130653266332,
          52.682428141563676
        ],
        [
          53.266331658291456,
          53.32833445489482
        ],
        [
          54.2713567839196,
          54.031944733497696
        ],
        [
          55.27638190954774,
          54.78814578704423
        ],
        [
          56.28140703517588,
          55.59130641506089
        ],
        [
          57.286432160804026,
          56.435320887052306
        ],
        [
          58.291457286432156,
          57.31365620174384
        ],
        [
          59.2964824120603,
          58.21940276159211
        ],
        [
          60.30150753768844,
          59.145328072317625
        ],
        [
          61.30653266331658,
          60.08393305381927
        ],
        [
          62.311557788944725,
          61.027510528616745
        ],
        [
          63.31658291457286,
          61.968205437090084
        ],
        [
          64.321608040201,
          62.89807631537376
        ],
        [
          65.32663316582915,
          63.80915756192141
        ],
        [
          66.33165829145729,
          64.69352201256083
        ],
        [
          67.33668341708542,
          65.54334334135491
        ],
        [
          68.34170854271356,
          66.35095780579293
        ],
        [
          69.34673366834171,
          67.10892485974941
        ],
        [
          70.35175879396985,
          67.8100861662237
        ],
        [
          71.35678391959799,
          68.44762255405246
        ],
        [
          72.36180904522614,
          69.0151084784694
        ],
        [
          73.36683417085426,
          69.50656356445674
        ],
        [
          74.37185929648241,
          69.91650083414139
        ],
        [
          75.37688442211056,
          70.23997124486584
        ],
        [
          76.38190954773869,
          70.47260419281312
        ],
        [
          77.38693467336684,
          70.61064366797149
        ],
        [
          78.39195979899498,
          70.6509797795485
        ],
        [
          79.39698492462311,
          70.59117540643133
        ],
        [
          80.40201005025126,
          70.42948776466605
        ],
        [
          81.4070351758794,
          70.16488472290858
        ],
        [
          82.41206030150754,
          69.79705573708172
        ],
        [
          83.41708542713567,
          69.32641731674809
        ],
        [
          84.42211055276381,
          68.75411297766112
        ],
        [
          85.42713567839196,
          68.08200767726157
        ],
        [
          86.4321608040201,
          67.31267677222152
        ],
        [
          87.43718592964824,
          66.44938957917552
        ],
        [
          88.44221105527639,
          65.49608766119664
        ],
        [
          89.44723618090453,
          64.45735800305528
        ],
        [
          90.45226130653266,
          63.33840127752854
        ],
        [
          91.4572864321608,
          62.14499544270984
        ],
        [
          92.46231155778895,
          60.88345494610621
        ],
        [
          93.46733668341709,
          59.5605858450365
        ],
        [
          94.47236180904522,
          58.18363718419232
        ],
        [
          95.47738693467338,
          56.760248999956424
        ],
        [
          96.4824120603015,
          55.298397346971164
        ],
        [
          97.48743718592965,
          53.80633676530895
        ],
        [
          98.49246231155779,
          52.29254062624751
        ],
        [
          99.49748743718592,
          50.765639810938985
        ],
        [
          100.50251256281406,
          49.23436018906104
        ],
        [
          101.50753768844221,
          47.7074593737525
        ],
        [
          102.51256281407035,
          46.19366323469106
        ],
        [
          103.5175879396985,
          44.70160265302885
        ],
        [
          104.52261306532664,
          43.23975100004357
        ],
        [
          105.52763819095476,
          41.81636281580771
        ],
        [
          106.53266331658291,
          40.439414154963515
        ],
        [
          107.53768844221105,
          39.1165450538938
        ],
        [
          108.5427135678392,
          37.855004557290165
        ],
        [
          109.54773869346735,
          36.66159872247145
        ],
        [
          110.55276381909547,
          35.542641996944745
        ],
        [
          111.55778894472361,
          34.50391233880337
        ],
        [
          112.56281407035176,
          33.550610420824505
        ],
        [
          113.5678391959799,
          32.68732322777849
        ],
        [
          114.57286432160805,
          31.917992322738424
        ],
        [
          115.57788944723617,
          31.24588702233889
        ],
        [
          116.58291457286431,
          30.673582683251926
        ],
        [
          117.58793969849246,
          30.202944262918283
        ],
        [
          118.5929648241206,
          29.835115277091425
        ],
        [
          119.59798994974875,
          29.570512235333947
        ],
        [
          120.60301507537687,
          29.40882459356866
        ],
        [
          121.60804020100502,
          29.349020220451504
        ],
        [
          122.61306532663316,
          29.389356332028527
        ],
        [
          123.61809045226131,
          29.527395807186885
        ],
        [
          124.62311557788945,
          29.76002875513416
        ],
        [
          125.6281407035176,
          30.083499165858623
        ],
        [
          126.63316582914572,
          30.493436435543266
        ],
        [
          127.63819095477386,
          30.984891521530603
        ],
        [
          128.643216080402,
          31.55237744594755
        ],
        [
          129.64824120603015,
          32.189913833776316
        ],
        [
          130.6532663316583,
          32.89107514025061
        ],
        [
          131.65829145728642,
          33.64904219420706
        ],
        [
          132.66331658291458,
          34.456656658645095
        ],
        [
          133.66834170854273,
          35.306477987439166
        ],
        [
          134.67336683417085,
          36.1908424380786
        ],
        [
          135.678391959799,
          37.10192368462626
        ],
        [
          136.68341708542712,
          38.03179456290991
        ],
        [
          137.68844221105527,
          38.972489471383255
        ],
        [
          138.69346733668343,
          39.91606694618073
        ],
        [
          139.69849246231155,
          40.85467192768237
        ],
        [
          140.7035175879397,
          41.78059723840789
        ],
        [
          141.70854271356782,
          42.68634379825615
        ],
        [
          142.71356783919597,
          43.564679112947694
        ],
        [
          143.71859296482413,
          44.40869358493911
        ],
        [
          144.72361809045228,
          45.21185421295577
        ],
        [
          145.7286432160804,
          45.96805526650231
        ],
        [
          146.73366834170852,
          46.67166554510517
        ],
        [
          147.73869346733667,
          47.317571858436324
        ],
        [
          148.74371859296483,
          47.90121839265995
        ],
        [
          149.74874371859298,
          48.41864166011015
        ],
        [
          150.75376884422113,
          48.86650076350215
        ],
        [
          151.75879396984925,
          49.24210274204082
        ],
        [
          152.76381909547737,
          49.543422804740196
        ],
        [
          153.76884422110552,
          49.76911929571386
        ],
        [
          154.77386934673368,
          49.91854327683539
        ],
        [
          155.77889447236183,
          49.99174265468849
        ],
        [
          156.78391959798995,
          48.578290874320345
        ],
        [
          157.78894472361807,
          48.67082662357418
        ],
        [
          158.79396984924622,
          48.76743506693742
        ],
        [
          159.79899497487438,
          48.866274637740446
        ],
        [
          160.80402010050253,
          48.96567482395338
        ],
        [
          161.80904522613065,
          49.06414337508521
        ],
        [
          162.8140703517588,
          49.1603706760609
        ],
        [
          163.81909547738692,
          49.253231378304946
        ],
        [
          164.82412060301507,
          49.34178340627501
        ],
        [
          165.82914572864323,
          49.425264484027984
        ],
        [
          166.83417085427135,
          49.503086350839695
        ],
        [
          167.8391959798995,
          49.574826857232935
        ],
        [
          168.84422110552762,
          49.640220152810166
        ],
        [
          169.84924623115577,
          49.69914519487218
        ],
        [
          170.85427135678393,
          49.75161282178699
        ],
        [
          171.85929648241205,
          49.79775164733543
        ],
        [
          172.8643216080402,
          49.837793041702625
        ],
        [
          173.86934673366835,
          49.872055471336374
        ],
        [
          174.87437185929647,
          49.900928473506994
        ],
        [
          175.87939698492463,
          49.92485654205629
        ],
        [
          176.88442211055278,
          49.94432319851974
        ],
        [
          177.8894472361809,
          49.95983551757531
        ],
        [
          178.89447236180905,
          49.97190936766831
        ],
        [
          179.8994974874372,
          49.98111945423447
        ],
        [
          180.90452261306532,
          49.98825411771574
        ],
        [
          181.90954773869348,
          49.99333563668804
        ],
        [
          182.9145728643216,
          49.99659204075511
        ],
        [
          183.91959798994975,
          49.99845885427502
        ],
        [
          184.9246231155779,
          49.99940216502652
        ],
        [
          185.92964824120602,
          49.999810996907115
        ],
        [
          186.93467336683418,
          49.999955705446425
        ],
        [
          187.9396984924623,
          49.99999374856866
        ],
        [
          188.94472361809045,
          49.999999719358165
        ],
        [
          189.9497487437186,
          49.99999999999912
        ],
        [
          190.95477386934675,
          49.953577163475664
        ],
        [
          191.95979899497488,
          49.97840778915339
        ],
        [
          192.964824120603,
          49.99151883723595
        ],
        [
          193.96984924623115,
          49.99729254221583
        ],
        [
          194.9748743718593,
          49.99934117441022
        ],
        [
          195.97989949748745,
          49.999890641190376
        ],
        [
          196.98492462311557,
          49.99998997610272
        ],
        [
          197.9899497487437,
          49.999999685279214
        ],
        [
          198.99497487437185,
          49.999999999265455
        ],
        [
          200.0,
          50.0
        ]
      ]
    }
  ]
}